simantha/Asset.py
simantha/Buffer.py
simantha/Machine.py
simantha/Maintainer.py
simantha/Part.py
simantha/Sink.py
simantha/Source.py
simantha/System.py
simantha/__init__.py
simantha/simulation.py
simantha/utils.py
simantha-0.1.1.dist-info/LICENSE.txt
simantha-0.1.1.dist-info/METADATA
simantha-0.1.1.dist-info/WHEEL
simantha-0.1.1.dist-info/top_level.txt
simantha-0.1.1.dist-info/RECORD
