Metadata-Version: 2.1
Name: simantha
Version: 0.1.1
Summary: Simulation of Manufacturing Systems
Home-page: https://github.com/m-hoff/simantha
Author: Michael Hoffman
Author-email: m.hoff4@gmail.com
License: UNKNOWN
Platform: UNKNOWN
Classifier: Programming Language :: Python :: 3
Classifier: Intended Audience :: Manufacturing
Classifier: Intended Audience :: Science/Research
Classifier: License :: OSI Approved :: MIT License
Classifier: Operating System :: OS Independent
License-File: LICENSE.txt
